LICENSE
MANIFEST.in
README.md
pyproject.toml
setup.py
monitor_folium/__init__.py
monitor_folium/trabalhoANA.py
monitor_folium.egg-info/PKG-INFO
monitor_folium.egg-info/SOURCES.txt
monitor_folium.egg-info/dependency_links.txt
monitor_folium.egg-info/requires.txt
monitor_folium.egg-info/top_level.txt
monitor_folium/frontend/build/asset-manifest.json
monitor_folium/frontend/build/bootstrap.min.css
monitor_folium/frontend/build/index.html
monitor_folium/frontend/build/static/js/main.01aa0574.js
monitor_folium/frontend/build/static/js/main.01aa0574.js.LICENSE.txt
monitor_folium/frontend/build/static/js/main.01aa0574.js.map
monitor_folium/monitor_folium/__init__.py
streamlit_modal/__init__.py
tests/test_frontend.py
tests/test_package.py
tests/test_release.py